LICENSE
README.md
setup.cfg
setup.py
tsclustering/__init__.py
tsclustering/barycenters.py
tsclustering/kmeans.py
tsclustering/metrics.py
tsclustering.egg-info/PKG-INFO
tsclustering.egg-info/SOURCES.txt
tsclustering.egg-info/dependency_links.txt
tsclustering.egg-info/requires.txt
tsclustering.egg-info/top_level.txt